{"symptoms":[{"adaptation-property":"RoadStatus","value":"FLUID"}],"rules-proposal":"{\"components\":[{\"id\":\"device.RoadSensor\",\"version\":\"1.0.0\"},{\"id\":\"device.Steering\",\"version\":\"1.0.0\"},{\"id\":\"device.Engine\",\"version\":\"1.0.0\"},{\"id\":\"driving.FallbackPlan.ParkInTheRoadShoulder\",\"version\":\"1.0.0\"},{\"id\":\"device.HumanSensors\",\"version\":\"1.0.0\"},{\"id\":\"device.DriverFaceMonitor\",\"version\":\"1.0.0\"},{\"id\":\"device.DriverSeatSensor\",\"version\":\"1.0.0\"},{\"id\":\"device.CopilotSeatSensor\",\"version\":\"1.0.0\"},{\"id\":\"device.HandsOnWheelSensor\",\"version\":\"1.0.0\"},{\"id\":\"interaction.NotificationService\",\"version\":\"1.0.0\"},{\"id\":\"interaction.DriverDisplay.VisualText\",\"version\":\"1.0.0\"},{\"id\":\"interaction.DriverDisplay.VisualIcon\",\"version\":\"1.0.0\"},{\"id\":\"interaction.Speakers.AuditorySound\",\"version\":\"1.0.0\"},{\"id\":\"interaction.DashboardDisplay.VisualText\",\"version\":\"1.0.0\"},{\"id\":\"device.LIDAR.FrontDistanceSensor\",\"version\":\"1.0.0\"},{\"id\":\"device.LIDAR.RearDistanceSensor\",\"version\":\"1.0.0\"},{\"id\":\"device.LIDAR.LeftDistanceSensor\",\"version\":\"1.0.0\"},{\"id\":\"device.LIDAR.RightDistanceSensor\",\"version\":\"1.0.0\"}],\"reference-model\":\"AutonomousCar\",\"bindings\":[{\"requiring\":{\"component\":{\"id\":\"driving.L3.HighwayChauffer\",\"version\":\"1.0.0\"},\"interface\":\"required_roadsensor\"},\"supplying\":{\"component\":{\"id\":\"device.RoadSensor\",\"version\":\"1.0.0\"},\"interface\":\"provided_sensor\"}},{\"requiring\":{\"component\":{\"id\":\"driving.L3.HighwayChauffer\",\"version\":\"1.0.0\"},\"interface\":\"required_steering\"},\"supplying\":{\"component\":{\"id\":\"device.Steering\",\"version\":\"1.0.0\"},\"interface\":\"provided_device\"}},{\"requiring\":{\"component\":{\"id\":\"driving.L3.HighwayChauffer\",\"version\":\"1.0.0\"},\"interface\":\"required_engine\"},\"supplying\":{\"component\":{\"id\":\"device.Engine\",\"version\":\"1.0.0\"},\"interface\":\"provided_device\"}},{\"requiring\":{\"component\":{\"id\":\"driving.L3.HighwayChauffer\",\"version\":\"1.0.0\"},\"interface\":\"required_fallbackplan\"},\"supplying\":{\"component\":{\"id\":\"driving.FallbackPlan.ParkInTheRoadShoulder\",\"version\":\"1.0.0\"},\"interface\":\"provided_drivingservice\"}},{\"requiring\":{\"component\":{\"id\":\"device.HumanSensors\",\"version\":\"1.0.0\"},\"interface\":\"required_facemonitor\"},\"supplying\":{\"component\":{\"id\":\"device.DriverFaceMonitor\",\"version\":\"1.0.0\"},\"interface\":\"provided_sensor\"}},{\"requiring\":{\"component\":{\"id\":\"device.HumanSensors\",\"version\":\"1.0.0\"},\"interface\":\"required_driverseatsensor\"},\"supplying\":{\"component\":{\"id\":\"device.DriverSeatSensor\",\"version\":\"1.0.0\"},\"interface\":\"provided_sensor\"}},{\"requiring\":{\"component\":{\"id\":\"device.HumanSensors\",\"version\":\"1.0.0\"},\"interface\":\"required_copilotseatsensor\"},\"supplying\":{\"component\":{\"id\":\"device.CopilotSeatSensor\",\"version\":\"1.0.0\"},\"interface\":\"provided_sensor\"}},{\"requiring\":{\"component\":{\"id\":\"device.HumanSensors\",\"version\":\"1.0.0\"},\"interface\":\"required_handsonwheelsensor\"},\"supplying\":{\"component\":{\"id\":\"device.HandsOnWheelSensor\",\"version\":\"1.0.0\"},\"interface\":\"provided_sensor\"}},{\"requiring\":{\"component\":{\"id\":\"driving.L3.HighwayChauffer\",\"version\":\"1.0.0\"},\"interface\":\"required_humansensors\"},\"supplying\":{\"component\":{\"id\":\"device.HumanSensors\",\"version\":\"1.0.0\"},\"interface\":\"provided_sensor\"}},{\"requiring\":{\"component\":{\"id\":\"interaction.NotificationService\",\"version\":\"1.0.0\"},\"interface\":\"required_mechanisms\"},\"supplying\":{\"component\":{\"id\":\"interaction.DriverDisplay.VisualText\",\"version\":\"1.0.0\"},\"interface\":\"provided_mechanism\"}},{\"requiring\":{\"component\":{\"id\":\"interaction.NotificationService\",\"version\":\"1.0.0\"},\"interface\":\"required_mechanisms\"},\"supplying\":{\"component\":{\"id\":\"interaction.DriverDisplay.VisualIcon\",\"version\":\"1.0.0\"},\"interface\":\"provided_mechanism\"}},{\"requiring\":{\"component\":{\"id\":\"interaction.NotificationService\",\"version\":\"1.0.0\"},\"interface\":\"required_mechanisms\"},\"supplying\":{\"component\":{\"id\":\"interaction.Speakers.AuditorySound\",\"version\":\"1.0.0\"},\"interface\":\"provided_mechanism\"}},{\"requiring\":{\"component\":{\"id\":\"interaction.NotificationService\",\"version\":\"1.0.0\"},\"interface\":\"required_mechanisms\"},\"supplying\":{\"component\":{\"id\":\"interaction.DashboardDisplay.VisualText\",\"version\":\"1.0.0\"},\"interface\":\"provided_mechanism\"}},{\"requiring\":{\"component\":{\"id\":\"driving.L3.HighwayChauffer\",\"version\":\"1.0.0\"},\"interface\":\"required_notificationservice\"},\"supplying\":{\"component\":{\"id\":\"interaction.NotificationService\",\"version\":\"1.0.0\"},\"interface\":\"provided_service\"}},{\"requiring\":{\"component\":{\"id\":\"driving.L3.HighwayChauffer\",\"version\":\"1.0.0\"},\"interface\":\"required_frontdistancesensor\"},\"supplying\":{\"component\":{\"id\":\"device.LIDAR.FrontDistanceSensor\",\"version\":\"1.0.0\"},\"interface\":\"provided_sensor\"}},{\"requiring\":{\"component\":{\"id\":\"driving.L3.HighwayChauffer\",\"version\":\"1.0.0\"},\"interface\":\"required_reardistancesensor\"},\"supplying\":{\"component\":{\"id\":\"device.LIDAR.RearDistanceSensor\",\"version\":\"1.0.0\"},\"interface\":\"provided_sensor\"}},{\"requiring\":{\"component\":{\"id\":\"driving.L3.HighwayChauffer\",\"version\":\"1.0.0\"},\"interface\":\"required_leftdistancesensor\"},\"supplying\":{\"component\":{\"id\":\"device.LIDAR.LeftDistanceSensor\",\"version\":\"1.0.0\"},\"interface\":\"provided_sensor\"}},{\"requiring\":{\"component\":{\"id\":\"driving.L3.HighwayChauffer\",\"version\":\"1.0.0\"},\"interface\":\"required_rightdistancesensor\"},\"supplying\":{\"component\":{\"id\":\"device.LIDAR.RightDistanceSensor\",\"version\":\"1.0.0\"},\"interface\":\"provided_sensor\"}}],\"id\":\"ADS_L3_4_AdaptationRule_202505251757070779\",\"timestamp\":\"202505251757070808\"}","correlation-id":"2ccf5974e6f94641b7e8cee68d234256","current-system-configurarion":"{\"components\":[{\"id\":\"device.RoadSensor\",\"version\":\"1.0.0\"},{\"id\":\"device.Steering\",\"version\":\"1.0.0\"},{\"id\":\"device.Engine\",\"version\":\"1.0.0\"},{\"id\":\"driving.FallbackPlan.ParkInTheRoadShoulder\",\"version\":\"1.0.0\"},{\"id\":\"device.HumanSensors\",\"version\":\"1.0.0\"},{\"id\":\"device.DriverFaceMonitor\",\"version\":\"1.0.0\"},{\"id\":\"device.DriverSeatSensor\",\"version\":\"1.0.0\"},{\"id\":\"device.CopilotSeatSensor\",\"version\":\"1.0.0\"},{\"id\":\"device.HandsOnWheelSensor\",\"version\":\"1.0.0\"},{\"id\":\"interaction.NotificationService\",\"version\":\"1.0.0\"},{\"id\":\"interaction.DriverDisplay.VisualText\",\"version\":\"1.0.0\"},{\"id\":\"interaction.DriverDisplay.VisualIcon\",\"version\":\"1.0.0\"},{\"id\":\"interaction.Speakers.AuditorySound\",\"version\":\"1.0.0\"},{\"id\":\"interaction.DashboardDisplay.VisualText\",\"version\":\"1.0.0\"},{\"id\":\"device.LIDAR.FrontDistanceSensor\",\"version\":\"1.0.0\"},{\"id\":\"device.LIDAR.RearDistanceSensor\",\"version\":\"1.0.0\"},{\"id\":\"device.LIDAR.LeftDistanceSensor\",\"version\":\"1.0.0\"},{\"id\":\"device.LIDAR.RightDistanceSensor\",\"version\":\"1.0.0\"}],\"reference-model\":\"AutonomousCar\",\"bindings\":[{\"requiring\":{\"component\":{\"id\":\"driving.L3.HighwayChauffer\",\"version\":\"1.0.0\"},\"interface\":\"required_roadsensor\"},\"supplying\":{\"component\":{\"id\":\"device.RoadSensor\",\"version\":\"1.0.0\"},\"interface\":\"provided_sensor\"}},{\"requiring\":{\"component\":{\"id\":\"driving.L3.HighwayChauffer\",\"version\":\"1.0.0\"},\"interface\":\"required_steering\"},\"supplying\":{\"component\":{\"id\":\"device.Steering\",\"version\":\"1.0.0\"},\"interface\":\"provided_device\"}},{\"requiring\":{\"component\":{\"id\":\"driving.L3.HighwayChauffer\",\"version\":\"1.0.0\"},\"interface\":\"required_engine\"},\"supplying\":{\"component\":{\"id\":\"device.Engine\",\"version\":\"1.0.0\"},\"interface\":\"provided_device\"}},{\"requiring\":{\"component\":{\"id\":\"driving.L3.HighwayChauffer\",\"version\":\"1.0.0\"},\"interface\":\"required_fallbackplan\"},\"supplying\":{\"component\":{\"id\":\"driving.FallbackPlan.ParkInTheRoadShoulder\",\"version\":\"1.0.0\"},\"interface\":\"provided_drivingservice\"}},{\"requiring\":{\"component\":{\"id\":\"device.HumanSensors\",\"version\":\"1.0.0\"},\"interface\":\"required_facemonitor\"},\"supplying\":{\"component\":{\"id\":\"device.DriverFaceMonitor\",\"version\":\"1.0.0\"},\"interface\":\"provided_sensor\"}},{\"requiring\":{\"component\":{\"id\":\"device.HumanSensors\",\"version\":\"1.0.0\"},\"interface\":\"required_driverseatsensor\"},\"supplying\":{\"component\":{\"id\":\"device.DriverSeatSensor\",\"version\":\"1.0.0\"},\"interface\":\"provided_sensor\"}},{\"requiring\":{\"component\":{\"id\":\"device.HumanSensors\",\"version\":\"1.0.0\"},\"interface\":\"required_copilotseatsensor\"},\"supplying\":{\"component\":{\"id\":\"device.CopilotSeatSensor\",\"version\":\"1.0.0\"},\"interface\":\"provided_sensor\"}},{\"requiring\":{\"component\":{\"id\":\"device.HumanSensors\",\"version\":\"1.0.0\"},\"interface\":\"required_handsonwheelsensor\"},\"supplying\":{\"component\":{\"id\":\"device.HandsOnWheelSensor\",\"version\":\"1.0.0\"},\"interface\":\"provided_sensor\"}},{\"requiring\":{\"component\":{\"id\":\"driving.L3.HighwayChauffer\",\"version\":\"1.0.0\"},\"interface\":\"required_humansensors\"},\"supplying\":{\"component\":{\"id\":\"device.HumanSensors\",\"version\":\"1.0.0\"},\"interface\":\"provided_sensor\"}},{\"requiring\":{\"component\":{\"id\":\"interaction.NotificationService\",\"version\":\"1.0.0\"},\"interface\":\"required_mechanisms\"},\"supplying\":{\"component\":{\"id\":\"interaction.DriverDisplay.VisualText\",\"version\":\"1.0.0\"},\"interface\":\"provided_mechanism\"}},{\"requiring\":{\"component\":{\"id\":\"interaction.NotificationService\",\"version\":\"1.0.0\"},\"interface\":\"required_mechanisms\"},\"supplying\":{\"component\":{\"id\":\"interaction.DriverDisplay.VisualIcon\",\"version\":\"1.0.0\"},\"interface\":\"provided_mechanism\"}},{\"requiring\":{\"component\":{\"id\":\"interaction.NotificationService\",\"version\":\"1.0.0\"},\"interface\":\"required_mechanisms\"},\"supplying\":{\"component\":{\"id\":\"interaction.Speakers.AuditorySound\",\"version\":\"1.0.0\"},\"interface\":\"provided_mechanism\"}},{\"requiring\":{\"component\":{\"id\":\"interaction.NotificationService\",\"version\":\"1.0.0\"},\"interface\":\"required_mechanisms\"},\"supplying\":{\"component\":{\"id\":\"interaction.DashboardDisplay.VisualText\",\"version\":\"1.0.0\"},\"interface\":\"provided_mechanism\"}},{\"requiring\":{\"component\":{\"id\":\"driving.L3.HighwayChauffer\",\"version\":\"1.0.0\"},\"interface\":\"required_notificationservice\"},\"supplying\":{\"component\":{\"id\":\"interaction.NotificationService\",\"version\":\"1.0.0\"},\"interface\":\"provided_service\"}},{\"requiring\":{\"component\":{\"id\":\"driving.L3.HighwayChauffer\",\"version\":\"1.0.0\"},\"interface\":\"required_frontdistancesensor\"},\"supplying\":{\"component\":{\"id\":\"device.LIDAR.FrontDistanceSensor\",\"version\":\"1.0.0\"},\"interface\":\"provided_sensor\"}},{\"requiring\":{\"component\":{\"id\":\"driving.L3.HighwayChauffer\",\"version\":\"1.0.0\"},\"interface\":\"required_reardistancesensor\"},\"supplying\":{\"component\":{\"id\":\"device.LIDAR.RearDistanceSensor\",\"version\":\"1.0.0\"},\"interface\":\"provided_sensor\"}},{\"requiring\":{\"component\":{\"id\":\"driving.L3.HighwayChauffer\",\"version\":\"1.0.0\"},\"interface\":\"required_leftdistancesensor\"},\"supplying\":{\"component\":{\"id\":\"device.LIDAR.LeftDistanceSensor\",\"version\":\"1.0.0\"},\"interface\":\"provided_sensor\"}},{\"requiring\":{\"component\":{\"id\":\"driving.L3.HighwayChauffer\",\"version\":\"1.0.0\"},\"interface\":\"required_rightdistancesensor\"},\"supplying\":{\"component\":{\"id\":\"device.LIDAR.RightDistanceSensor\",\"version\":\"1.0.0\"},\"interface\":\"provided_sensor\"}},{\"requiring\":{\"component\":{\"id\":\"driving.L3.TrafficJamChauffer\",\"version\":\"1.0.0\"},\"interface\":\"required_roadsensor\"},\"supplying\":{\"component\":{\"id\":\"device.RoadSensor\",\"version\":\"1.0.0\"},\"interface\":\"provided_sensor\"}},{\"requiring\":{\"component\":{\"id\":\"driving.L3.TrafficJamChauffer\",\"version\":\"1.0.0\"},\"interface\":\"required_steering\"},\"supplying\":{\"component\":{\"id\":\"device.Steering\",\"version\":\"1.0.0\"},\"interface\":\"provided_device\"}},{\"requiring\":{\"component\":{\"id\":\"driving.L3.TrafficJamChauffer\",\"version\":\"1.0.0\"},\"interface\":\"required_engine\"},\"supplying\":{\"component\":{\"id\":\"device.Engine\",\"version\":\"1.0.0\"},\"interface\":\"provided_device\"}},{\"requiring\":{\"component\":{\"id\":\"driving.L3.TrafficJamChauffer\",\"version\":\"1.0.0\"},\"interface\":\"required_fallbackplan\"},\"supplying\":{\"component\":{\"id\":\"driving.FallbackPlan.ParkInTheRoadShoulder\",\"version\":\"1.0.0\"},\"interface\":\"provided_drivingservice\"}},{\"requiring\":{\"component\":{\"id\":\"driving.L3.TrafficJamChauffer\",\"version\":\"1.0.0\"},\"interface\":\"required_humansensors\"},\"supplying\":{\"component\":{\"id\":\"device.HumanSensors\",\"version\":\"1.0.0\"},\"interface\":\"provided_sensor\"}},{\"requiring\":{\"component\":{\"id\":\"driving.L3.TrafficJamChauffer\",\"version\":\"1.0.0\"},\"interface\":\"required_notificationservice\"},\"supplying\":{\"component\":{\"id\":\"interaction.NotificationService\",\"version\":\"1.0.0\"},\"interface\":\"provided_service\"}},{\"requiring\":{\"component\":{\"id\":\"driving.L3.TrafficJamChauffer\",\"version\":\"1.0.0\"},\"interface\":\"required_frontdistancesensor\"},\"supplying\":{\"component\":{\"id\":\"device.LIDAR.FrontDistanceSensor\",\"version\":\"1.0.0\"},\"interface\":\"provided_sensor\"}},{\"requiring\":{\"component\":{\"id\":\"driving.L3.TrafficJamChauffer\",\"version\":\"1.0.0\"},\"interface\":\"required_reardistancesensor\"},\"supplying\":{\"component\":{\"id\":\"device.LIDAR.RearDistanceSensor\",\"version\":\"1.0.0\"},\"interface\":\"provided_sensor\"}},{\"requiring\":{\"component\":{\"id\":\"driving.L3.TrafficJamChauffer\",\"version\":\"1.0.0\"},\"interface\":\"required_leftdistancesensor\"},\"supplying\":{\"component\":{\"id\":\"device.LIDAR.LeftDistanceSensor\",\"version\":\"1.0.0\"},\"interface\":\"provided_sensor\"}},{\"requiring\":{\"component\":{\"id\":\"driving.L3.TrafficJamChauffer\",\"version\":\"1.0.0\"},\"interface\":\"required_rightdistancesensor\"},\"supplying\":{\"component\":{\"id\":\"device.LIDAR.RightDistanceSensor\",\"version\":\"1.0.0\"},\"interface\":\"provided_sensor\"}}],\"id\":\"ADS_L3_2_AdaptationRule_202505251753560165\",\"timestamp\":\"202505251757070808\"}","next-system-configurarion":"{\"components\":[{\"id\":\"device.RoadSensor\",\"version\":\"1.0.0\"},{\"id\":\"device.Steering\",\"version\":\"1.0.0\"},{\"id\":\"device.Engine\",\"version\":\"1.0.0\"},{\"id\":\"driving.FallbackPlan.ParkInTheRoadShoulder\",\"version\":\"1.0.0\"},{\"id\":\"device.HumanSensors\",\"version\":\"1.0.0\"},{\"id\":\"device.DriverFaceMonitor\",\"version\":\"1.0.0\"},{\"id\":\"device.DriverSeatSensor\",\"version\":\"1.0.0\"},{\"id\":\"device.CopilotSeatSensor\",\"version\":\"1.0.0\"},{\"id\":\"device.HandsOnWheelSensor\",\"version\":\"1.0.0\"},{\"id\":\"interaction.NotificationService\",\"version\":\"1.0.0\"},{\"id\":\"interaction.DriverDisplay.VisualText\",\"version\":\"1.0.0\"},{\"id\":\"interaction.DriverDisplay.VisualIcon\",\"version\":\"1.0.0\"},{\"id\":\"interaction.Speakers.AuditorySound\",\"version\":\"1.0.0\"},{\"id\":\"interaction.DashboardDisplay.VisualText\",\"version\":\"1.0.0\"},{\"id\":\"device.LIDAR.FrontDistanceSensor\",\"version\":\"1.0.0\"},{\"id\":\"device.LIDAR.RearDistanceSensor\",\"version\":\"1.0.0\"},{\"id\":\"device.LIDAR.LeftDistanceSensor\",\"version\":\"1.0.0\"},{\"id\":\"device.LIDAR.RightDistanceSensor\",\"version\":\"1.0.0\"}],\"reference-model\":\"AutonomousCar\",\"bindings\":[{\"requiring\":{\"component\":{\"id\":\"driving.L3.HighwayChauffer\",\"version\":\"1.0.0\"},\"interface\":\"required_roadsensor\"},\"supplying\":{\"component\":{\"id\":\"device.RoadSensor\",\"version\":\"1.0.0\"},\"interface\":\"provided_sensor\"}},{\"requiring\":{\"component\":{\"id\":\"driving.L3.HighwayChauffer\",\"version\":\"1.0.0\"},\"interface\":\"required_steering\"},\"supplying\":{\"component\":{\"id\":\"device.Steering\",\"version\":\"1.0.0\"},\"interface\":\"provided_device\"}},{\"requiring\":{\"component\":{\"id\":\"driving.L3.HighwayChauffer\",\"version\":\"1.0.0\"},\"interface\":\"required_engine\"},\"supplying\":{\"component\":{\"id\":\"device.Engine\",\"version\":\"1.0.0\"},\"interface\":\"provided_device\"}},{\"requiring\":{\"component\":{\"id\":\"driving.L3.HighwayChauffer\",\"version\":\"1.0.0\"},\"interface\":\"required_fallbackplan\"},\"supplying\":{\"component\":{\"id\":\"driving.FallbackPlan.ParkInTheRoadShoulder\",\"version\":\"1.0.0\"},\"interface\":\"provided_drivingservice\"}},{\"requiring\":{\"component\":{\"id\":\"device.HumanSensors\",\"version\":\"1.0.0\"},\"interface\":\"required_facemonitor\"},\"supplying\":{\"component\":{\"id\":\"device.DriverFaceMonitor\",\"version\":\"1.0.0\"},\"interface\":\"provided_sensor\"}},{\"requiring\":{\"component\":{\"id\":\"device.HumanSensors\",\"version\":\"1.0.0\"},\"interface\":\"required_driverseatsensor\"},\"supplying\":{\"component\":{\"id\":\"device.DriverSeatSensor\",\"version\":\"1.0.0\"},\"interface\":\"provided_sensor\"}},{\"requiring\":{\"component\":{\"id\":\"device.HumanSensors\",\"version\":\"1.0.0\"},\"interface\":\"required_copilotseatsensor\"},\"supplying\":{\"component\":{\"id\":\"device.CopilotSeatSensor\",\"version\":\"1.0.0\"},\"interface\":\"provided_sensor\"}},{\"requiring\":{\"component\":{\"id\":\"device.HumanSensors\",\"version\":\"1.0.0\"},\"interface\":\"required_handsonwheelsensor\"},\"supplying\":{\"component\":{\"id\":\"device.HandsOnWheelSensor\",\"version\":\"1.0.0\"},\"interface\":\"provided_sensor\"}},{\"requiring\":{\"component\":{\"id\":\"driving.L3.HighwayChauffer\",\"version\":\"1.0.0\"},\"interface\":\"required_humansensors\"},\"supplying\":{\"component\":{\"id\":\"device.HumanSensors\",\"version\":\"1.0.0\"},\"interface\":\"provided_sensor\"}},{\"requiring\":{\"component\":{\"id\":\"interaction.NotificationService\",\"version\":\"1.0.0\"},\"interface\":\"required_mechanisms\"},\"supplying\":{\"component\":{\"id\":\"interaction.DriverDisplay.VisualText\",\"version\":\"1.0.0\"},\"interface\":\"provided_mechanism\"}},{\"requiring\":{\"component\":{\"id\":\"interaction.NotificationService\",\"version\":\"1.0.0\"},\"interface\":\"required_mechanisms\"},\"supplying\":{\"component\":{\"id\":\"interaction.DriverDisplay.VisualIcon\",\"version\":\"1.0.0\"},\"interface\":\"provided_mechanism\"}},{\"requiring\":{\"component\":{\"id\":\"interaction.NotificationService\",\"version\":\"1.0.0\"},\"interface\":\"required_mechanisms\"},\"supplying\":{\"component\":{\"id\":\"interaction.Speakers.AuditorySound\",\"version\":\"1.0.0\"},\"interface\":\"provided_mechanism\"}},{\"requiring\":{\"component\":{\"id\":\"interaction.NotificationService\",\"version\":\"1.0.0\"},\"interface\":\"required_mechanisms\"},\"supplying\":{\"component\":{\"id\":\"interaction.DashboardDisplay.VisualText\",\"version\":\"1.0.0\"},\"interface\":\"provided_mechanism\"}},{\"requiring\":{\"component\":{\"id\":\"driving.L3.HighwayChauffer\",\"version\":\"1.0.0\"},\"interface\":\"required_notificationservice\"},\"supplying\":{\"component\":{\"id\":\"interaction.NotificationService\",\"version\":\"1.0.0\"},\"interface\":\"provided_service\"}},{\"requiring\":{\"component\":{\"id\":\"driving.L3.HighwayChauffer\",\"version\":\"1.0.0\"},\"interface\":\"required_frontdistancesensor\"},\"supplying\":{\"component\":{\"id\":\"device.LIDAR.FrontDistanceSensor\",\"version\":\"1.0.0\"},\"interface\":\"provided_sensor\"}},{\"requiring\":{\"component\":{\"id\":\"driving.L3.HighwayChauffer\",\"version\":\"1.0.0\"},\"interface\":\"required_reardistancesensor\"},\"supplying\":{\"component\":{\"id\":\"device.LIDAR.RearDistanceSensor\",\"version\":\"1.0.0\"},\"interface\":\"provided_sensor\"}},{\"requiring\":{\"component\":{\"id\":\"driving.L3.HighwayChauffer\",\"version\":\"1.0.0\"},\"interface\":\"required_leftdistancesensor\"},\"supplying\":{\"component\":{\"id\":\"device.LIDAR.LeftDistanceSensor\",\"version\":\"1.0.0\"},\"interface\":\"provided_sensor\"}},{\"requiring\":{\"component\":{\"id\":\"driving.L3.HighwayChauffer\",\"version\":\"1.0.0\"},\"interface\":\"required_rightdistancesensor\"},\"supplying\":{\"component\":{\"id\":\"device.LIDAR.RightDistanceSensor\",\"version\":\"1.0.0\"},\"interface\":\"provided_sensor\"}},{\"requiring\":{\"component\":{\"id\":\"driving.L3.TrafficJamChauffer\",\"version\":\"1.0.0\"},\"interface\":\"required_roadsensor\"},\"supplying\":{\"component\":{\"id\":\"device.RoadSensor\",\"version\":\"1.0.0\"},\"interface\":\"provided_sensor\"}},{\"requiring\":{\"component\":{\"id\":\"driving.L3.TrafficJamChauffer\",\"version\":\"1.0.0\"},\"interface\":\"required_steering\"},\"supplying\":{\"component\":{\"id\":\"device.Steering\",\"version\":\"1.0.0\"},\"interface\":\"provided_device\"}},{\"requiring\":{\"component\":{\"id\":\"driving.L3.TrafficJamChauffer\",\"version\":\"1.0.0\"},\"interface\":\"required_engine\"},\"supplying\":{\"component\":{\"id\":\"device.Engine\",\"version\":\"1.0.0\"},\"interface\":\"provided_device\"}},{\"requiring\":{\"component\":{\"id\":\"driving.L3.TrafficJamChauffer\",\"version\":\"1.0.0\"},\"interface\":\"required_fallbackplan\"},\"supplying\":{\"component\":{\"id\":\"driving.FallbackPlan.ParkInTheRoadShoulder\",\"version\":\"1.0.0\"},\"interface\":\"provided_drivingservice\"}},{\"requiring\":{\"component\":{\"id\":\"driving.L3.TrafficJamChauffer\",\"version\":\"1.0.0\"},\"interface\":\"required_humansensors\"},\"supplying\":{\"component\":{\"id\":\"device.HumanSensors\",\"version\":\"1.0.0\"},\"interface\":\"provided_sensor\"}},{\"requiring\":{\"component\":{\"id\":\"driving.L3.TrafficJamChauffer\",\"version\":\"1.0.0\"},\"interface\":\"required_notificationservice\"},\"supplying\":{\"component\":{\"id\":\"interaction.NotificationService\",\"version\":\"1.0.0\"},\"interface\":\"provided_service\"}},{\"requiring\":{\"component\":{\"id\":\"driving.L3.TrafficJamChauffer\",\"version\":\"1.0.0\"},\"interface\":\"required_frontdistancesensor\"},\"supplying\":{\"component\":{\"id\":\"device.LIDAR.FrontDistanceSensor\",\"version\":\"1.0.0\"},\"interface\":\"provided_sensor\"}},{\"requiring\":{\"component\":{\"id\":\"driving.L3.TrafficJamChauffer\",\"version\":\"1.0.0\"},\"interface\":\"required_reardistancesensor\"},\"supplying\":{\"component\":{\"id\":\"device.LIDAR.RearDistanceSensor\",\"version\":\"1.0.0\"},\"interface\":\"provided_sensor\"}},{\"requiring\":{\"component\":{\"id\":\"driving.L3.TrafficJamChauffer\",\"version\":\"1.0.0\"},\"interface\":\"required_leftdistancesensor\"},\"supplying\":{\"component\":{\"id\":\"device.LIDAR.LeftDistanceSensor\",\"version\":\"1.0.0\"},\"interface\":\"provided_sensor\"}},{\"requiring\":{\"component\":{\"id\":\"driving.L3.TrafficJamChauffer\",\"version\":\"1.0.0\"},\"interface\":\"required_rightdistancesensor\"},\"supplying\":{\"component\":{\"id\":\"device.LIDAR.RightDistanceSensor\",\"version\":\"1.0.0\"},\"interface\":\"provided_sensor\"}}],\"id\":\"ADS_L3_4_AdaptationRule_202505251757070779\",\"timestamp\":\"202505251757070808\"}","id":"report-2ccf5974e6f94641b7e8cee68d234256","initiated-by-rule":"ADS_L3_4_AdaptationRule","timestamp":"202505251757070808","status":[{"status":"REQUESTED","timestamp":"202505251757070778"},{"status":"IN_PROGRESS","timestamp":"202505251757070780"},{"value":"No Adaptation Plan required","status":"EXITED","timestamp":"202505251757070807"}]}